ifbo/__init__.py
ifbo/bar_distribution.py
ifbo/decoders.py
ifbo/download.py
ifbo/encoders.py
ifbo/initializers.py
ifbo/layer.py
ifbo/positional_encodings.py
ifbo/surrogate.py
ifbo/train.py
ifbo/transformer.py
ifbo/utils.py
ifbo/version.py
ifbo/priors/__init__.py
ifbo/priors/ftpfn_prior.py
ifbo/priors/output_sorted.npy
ifbo/priors/prior.py
ifbo/priors/prior_bag.py
ifbo/priors/utils.py
ifbo-0.3.13.dist-info/METADATA
ifbo-0.3.13.dist-info/WHEEL
ifbo-0.3.13.dist-info/top_level.txt
ifbo-0.3.13.dist-info/RECORD
