Metadata-Version: 2.4
Name: ifBO
Version: 0.3.13
Summary: In-context Freeze-Thaw Bayesian Optimization for Hyperparameter Optimization
Author: Samir Garibov, Edward Bergman, Frank Hutter
Author-email: Herilalaina Rakotoarison <rakotoah@cs.uni-freiburg.de>, Steven Adriaensen <adriaens@cs.uni-freiburg.de>, Neeratyoy Mallik <mallik@cs.uni-freiburg.de>
License: MIT License
Project-URL: homepage, https://github.com/automl/ifBO
Project-URL: repository, https://github.com/automl/ifBO
Project-URL: bugtracker, https://github.com/automl/ifBO/issues
Classifier: Intended Audience :: Science/Research
Classifier: License :: OSI Approved :: MIT License
Classifier: Programming Language :: Python
Classifier: Topic :: Software Development
Classifier: Topic :: Scientific/Engineering
Classifier: Operating System :: Unix
Classifier: Operating System :: MacOS
Classifier: Programming Language :: Python :: 3
Classifier: Programming Language :: Python :: 3.10
Classifier: Programming Language :: Python :: 3.11
Classifier: Programming Language :: Python :: 3.12
Classifier: Programming Language :: Python :: 3.13
Requires-Python: <3.14,>=3.10
Requires-Dist: cloudpickle>=3.0.0
Requires-Dist: torch>=1.9.0
Requires-Dist: numpy>=1.21.2
Requires-Dist: scipy>=1.13.1
Requires-Dist: requests>=2.23.0
Requires-Dist: submitit>=1.5.1
Provides-Extra: checking
Requires-Dist: pre-commit; extra == "checking"
Requires-Dist: mypy; extra == "checking"
Requires-Dist: ruff; extra == "checking"
